MANIFEST.in
README.md
setup.py
dbt/__init__.py
dbt/adapters/clickzetta/__init__.py
dbt/adapters/clickzetta/__version__.py
dbt/adapters/clickzetta/column.py
dbt/adapters/clickzetta/connections.py
dbt/adapters/clickzetta/impl.py
dbt/adapters/clickzetta/relation.py
dbt/include/clickzetta/__init__.py
dbt/include/clickzetta/dbt_project.yml
dbt/include/clickzetta/profile_template.yml
dbt/include/clickzetta/macros/adapters.sql
dbt/include/clickzetta/macros/materializations/seed.sql
dbt/include/clickzetta/macros/materializations/snapshot.sql
dbt/include/clickzetta/macros/materializations/table.sql
dbt/include/clickzetta/macros/materializations/view.sql
dbt/include/clickzetta/macros/materializations/incremental/column_helpers.sql
dbt/include/clickzetta/macros/materializations/incremental/incremental.sql
dbt/include/clickzetta/macros/materializations/incremental/strategies.sql
dbt/include/clickzetta/macros/materializations/incremental/validate.sql
dbt/include/clickzetta/macros/utils/any_value.sql
dbt/include/clickzetta/macros/utils/array_append.sql
dbt/include/clickzetta/macros/utils/array_concat.sql
dbt/include/clickzetta/macros/utils/array_construct.sql
dbt/include/clickzetta/macros/utils/assert_not_null.sql
dbt/include/clickzetta/macros/utils/bool_or.sql
dbt/include/clickzetta/macros/utils/concat.sql
dbt/include/clickzetta/macros/utils/dateadd.sql
dbt/include/clickzetta/macros/utils/datediff.sql
dbt/include/clickzetta/macros/utils/escape_single_quotes.sql
dbt/include/clickzetta/macros/utils/listagg.sql
dbt/include/clickzetta/macros/utils/nullcheck.sql
dbt/include/clickzetta/macros/utils/split_part.sql
dbt/include/clickzetta/macros/utils/timestamps.sql
dbt_clickzetta.egg-info/PKG-INFO
dbt_clickzetta.egg-info/SOURCES.txt
dbt_clickzetta.egg-info/dependency_links.txt
dbt_clickzetta.egg-info/not-zip-safe
dbt_clickzetta.egg-info/requires.txt
dbt_clickzetta.egg-info/top_level.txt